{
    "nodes": [
        {
            "ix": "7-697_v1_report34688_0",
            "content": "Reviewer response for version 1",
            "ntype": "article-title",
            "meta": {
                "created_by": "F1000XMLParser"
            }
        },
        {
            "ix": "7-697_v1_report34688_1",
            "content": "Overall your paper is very good and well done, but here are some minor suggestions:",
            "ntype": "p",
            "meta": {
                "created_by": "F1000XMLParser"
            }
        },
        {
            "ix": "7-697_v1_report34688_2",
            "content": "- Could you please state more about the Kjellberg\u2019s technique, it is not well described in the methods section of your paper?\n- Could you please inform about the study design (descriptive or analytic study)?\n- Could you please inform about the sampling method and how to determine the sample size?\n- You only mention the inclusion criteria, what about the exclusion criteria? Please mention it.\n- Please mention and inform who examined the patient? How to examine the patient? Please explain.\n- How about the competency of the examiner? How many people? How to calibrate each examiner\u2019s perception. Please mention also who is in charge for radiographic image interpretation?",
            "ntype": "list",
            "meta": {
                "created_by": "F1000XMLParser"
            }
        }
    ],
    "span_nodes": [
        {
            "ix": "7-697_v1_report34688_0@0",
            "content": "Reviewer response for version 1",
            "ntype": "s",
            "meta": {
                "created_by": "IntertextSentenceSplitter_all"
            },
            "src_ix": "7-697_v1_report34688_0",
            "start": 0,
            "end": 30,
            "label": {}
        },
        {
            "ix": "7-697_v1_report34688_1@0",
            "content": "Overall your paper is very good and well done, but here are some minor suggestions:",
            "ntype": "s",
            "meta": {
                "created_by": "IntertextSentenceSplitter_all"
            },
            "src_ix": "7-697_v1_report34688_1",
            "start": 0,
            "end": 82,
            "label": {}
        },
        {
            "ix": "7-697_v1_report34688_2@0",
            "content": "- Could you please state more about the Kjellberg\u2019s technique, it is not well described in the methods section of your paper?",
            "ntype": "s",
            "meta": {
                "created_by": "IntertextSentenceSplitter_all"
            },
            "src_ix": "7-697_v1_report34688_2",
            "start": 0,
            "end": 124,
            "label": {}
        },
        {
            "ix": "7-697_v1_report34688_2@1",
            "content": "- Could you please inform about the study design (descriptive or analytic study)?",
            "ntype": "s",
            "meta": {
                "created_by": "IntertextSentenceSplitter_all"
            },
            "src_ix": "7-697_v1_report34688_2",
            "start": 126,
            "end": 206,
            "label": {}
        },
        {
            "ix": "7-697_v1_report34688_2@2",
            "content": "- Could you please inform about the sampling method and how to determine the sample size?",
            "ntype": "s",
            "meta": {
                "created_by": "IntertextSentenceSplitter_all"
            },
            "src_ix": "7-697_v1_report34688_2",
            "start": 208,
            "end": 296,
            "label": {}
        },
        {
            "ix": "7-697_v1_report34688_2@3",
            "content": "- You only mention the inclusion criteria, what about the exclusion criteria? Please mention it.",
            "ntype": "s",
            "meta": {
                "created_by": "IntertextSentenceSplitter_all"
            },
            "src_ix": "7-697_v1_report34688_2",
            "start": 298,
            "end": 393,
            "label": {}
        },
        {
            "ix": "7-697_v1_report34688_2@4",
            "content": "- Please mention and inform who examined the patient? How to examine the patient? Please explain.",
            "ntype": "s",
            "meta": {
                "created_by": "IntertextSentenceSplitter_all"
            },
            "src_ix": "7-697_v1_report34688_2",
            "start": 395,
            "end": 491,
            "label": {}
        },
        {
            "ix": "7-697_v1_report34688_2@5",
            "content": "- How about the competency of the examiner? How many people? How to calibrate each examiner\u2019s perception. Please mention also who is in charge for radiographic image interpretation?",
            "ntype": "s",
            "meta": {
                "created_by": "IntertextSentenceSplitter_all"
            },
            "src_ix": "7-697_v1_report34688_2",
            "start": 493,
            "end": 673,
            "label": {}
        }
    ],
    "edges": [
        {
            "src_ix": "7-697_v1_report34688_0",
            "tgt_ix": "7-697_v1_report34688_1",
            "etype": "parent",
            "meta": {
                "created_by": "F1000XMLParser"
            }
        },
        {
            "src_ix": "7-697_v1_report34688_0",
            "tgt_ix": "7-697_v1_report34688_2",
            "etype": "parent",
            "meta": {
                "created_by": "F1000XMLParser"
            }
        },
        {
            "src_ix": "7-697_v1_report34688_0",
            "tgt_ix": "7-697_v1_report34688_1",
            "etype": "next",
            "meta": {
                "created_by": "F1000XMLParser"
            }
        },
        {
            "src_ix": "7-697_v1_report34688_1",
            "tgt_ix": "7-697_v1_report34688_2",
            "etype": "next",
            "meta": {
                "created_by": "F1000XMLParser"
            }
        },
        {
            "src_ix": "7-697_v1_report34688_0",
            "tgt_ix": "7-697_v1_report34688_0@0",
            "etype": "link",
            "meta": {
                "created_by": "IntertextSentenceSplitter_all"
            }
        },
        {
            "src_ix": "7-697_v1_report34688_1",
            "tgt_ix": "7-697_v1_report34688_1@0",
            "etype": "link",
            "meta": {
                "created_by": "IntertextSentenceSplitter_all"
            }
        },
        {
            "src_ix": "7-697_v1_report34688_2",
            "tgt_ix": "7-697_v1_report34688_2@0",
            "etype": "link",
            "meta": {
                "created_by": "IntertextSentenceSplitter_all"
            }
        },
        {
            "src_ix": "7-697_v1_report34688_2",
            "tgt_ix": "7-697_v1_report34688_2@1",
            "etype": "link",
            "meta": {
                "created_by": "IntertextSentenceSplitter_all"
            }
        },
        {
            "src_ix": "7-697_v1_report34688_2",
            "tgt_ix": "7-697_v1_report34688_2@2",
            "etype": "link",
            "meta": {
                "created_by": "IntertextSentenceSplitter_all"
            }
        },
        {
            "src_ix": "7-697_v1_report34688_2",
            "tgt_ix": "7-697_v1_report34688_2@3",
            "etype": "link",
            "meta": {
                "created_by": "IntertextSentenceSplitter_all"
            }
        },
        {
            "src_ix": "7-697_v1_report34688_2",
            "tgt_ix": "7-697_v1_report34688_2@4",
            "etype": "link",
            "meta": {
                "created_by": "IntertextSentenceSplitter_all"
            }
        },
        {
            "src_ix": "7-697_v1_report34688_2",
            "tgt_ix": "7-697_v1_report34688_2@5",
            "etype": "link",
            "meta": {
                "created_by": "IntertextSentenceSplitter_all"
            }
        }
    ],
    "prefix": "7-697_v1_report34688",
    "meta": {
        "review_id": "7-697_v1_report34688",
        "license": "http://creativecommons.org/licenses/by/4.0/",
        "recommendation": "approve",
        "doi": "10.5256/f1000research.15809.r34688",
        "contributors": [
            {
                "surname": "Narmada",
                "given-names": "Ida Bagus"
            }
        ],
        "ix_counter": 13,
        "sentence_split_type": "HybridSplitterLessAndLong",
        "sentence_split_model": "HybridSplitterLessAndLong_SciSpacy+Spacy"
    }
}